pymusicxml/__init__.py
pymusicxml/_utilities.py
pymusicxml/directions.py
pymusicxml/enums.py
pymusicxml/notations.py
pymusicxml/score_components.py
pymusicxml/spanners.py
pymusicxml-0.5.5.dist-info/LICENSE
pymusicxml-0.5.5.dist-info/METADATA
pymusicxml-0.5.5.dist-info/WHEEL
pymusicxml-0.5.5.dist-info/top_level.txt
pymusicxml-0.5.5.dist-info/RECORD
