Metadata-Version: 2.1
Name: pymusicxml
Version: 0.5.5
Summary: A simple python library for exporting MusicXML
Home-page: https://git.sr.ht/~marcevanstein/pymusicxml
Author: Marc Evanstein
Author-email: marc@marcevanstein.com
License: UNKNOWN
Platform: UNKNOWN
Classifier: Programming Language :: Python :: 3
Classifier: License :: OSI Approved :: GNU General Public License v3 (GPLv3)
Classifier: Operating System :: OS Independent
